{
  "title": "My Balance",
  "availableBalance": "Available Balance",
  "totalBalance": "Total Balance",
  "frozen": "Frozen",
  "deposit": "Deposit",
  "withdraw": "Withdraw",
  "recentTransactions": "Recent Transactions",
  "viewAllTransactions": "View all transactions",
  "errorLoading": "Error loading balance",
  "depositFunds": "Deposit Funds",
  "withdrawFunds": "Withdraw Funds",
  "selectAmount": "Select amount",
  "customAmount": "Custom amount",
  "paymentMethod": "Payment method",
  "continueToPayment": "Continue to payment",
  "transactionHistory": "Transaction History",
  "transaction": {
    "deposit": "Deposit",
    "withdrawal": "Withdrawal",
    "payment": "Payment",
    "refund": "Refund",
    "commission": "Commission",
    "escrow_release": "Escrow Release",
    "escrow_hold": "Escrow Hold"
  },
  "status": {
    "pending": "Pending",
    "completed": "Completed",
    "failed": "Failed",
    "processing": "Processing"
  },
  "error": {
    "invalid_user_id": "Invalid user ID",
    "fetch_balance_failed": "Failed to fetch user balance",
    "fetch_transactions_failed": "Failed to fetch user transactions",
    "deposit_failed": "Failed to create deposit",
    "withdrawal_failed": "Failed to create withdrawal"
  },
  "limits": "Minimum: 100 RSD, Maximum: 100,000 RSD",
  "bankCard": "Bank Card",
  "supportedCards": "Visa, Mastercard, Maestro",
  "amountToDeposit": "Amount to deposit",
  "commission": "Commission",
  "toCredit": "To credit",
  "securePayment": "Secure payment through protected connection",
  "information": "Information",
  "instantCredit": "Funds are credited instantly",
  "minAmount": "Minimum amount",
  "maxAmount": "Maximum amount",
  "noCommission": "Deposit commission",
  "supportedCurrencies": "Supported currencies",
  "needHelp": "Need help?",
  "supportMessage": "If you experience issues with deposit, contact support.",
  "contactSupport": "Contact Support"
}
