{
  "deliveryMethod": "Delivery Method",
  "courierDelivery": "Courier Delivery",
  "postOffice": "Post Office",
  "warehousePickup": "Warehouse Pickup",
  "selectMethod": "Select delivery method",
  "selectAddress": "Delivery address",
  "selectOffice": "Select office",
  "recipientDetails": "Recipient details",
  "deliveryInstructions": "Delivery instructions",
  "estimatedDelivery": "Estimated delivery",
  "deliveryCost": "Delivery cost",
  "free": "Free",
  "calculateRate": "Calculate rate",
  "rateCalculated": "Rate calculated",
  "trackingNumber": "Tracking number",
  "trackPackage": "Track package",
  "pickupCode": "Pickup code",
  "warehouseAddress": "Warehouse address",
  "workingHours": "Working hours",
  "deliveryTime": "Delivery time",
  "businessDays": "business days",
  "standardDelivery": "Standard delivery",
  "expressDelivery": "Express delivery",
  "codSupported": "Cash on delivery supported",
  "insuranceIncluded": "Insurance included",
  "smsNotifications": "SMS notifications",
  "errors": {
    "methodRequired": "Please select a delivery method",
    "addressRequired": "Please enter delivery address",
    "officeRequired": "Please select a post office",
    "calculationFailed": "Failed to calculate delivery cost"
  }
}
